o3iss-0.1.3.dist-info/RECORD
o3iss-0.1.3.dist-info/WHEEL
o3iss-0.1.3.dist-info/METADATA
o3iss-0.1.3.dist-info/top_level.txt
o3iss-0.1.3.dist-info/LICENSE
o3iss/_sklearn.py
o3iss/o3iss.cpython-39-x86_64-linux-gnu.so
o3iss/__init__.py
