Metadata-Version: 2.1
Name: o3iss
Version: 0.1.3
Summary: Iterated-sums signature in Rust
Home-page: https://github.com/ntapiam/o3iss
Author: Nikolas Tapia
Author-email: tapia@wias-berlin.de
License: UNKNOWN
Platform: UNKNOWN
Classifier: Programming Language :: Rust
Classifier: Programming Language :: Python
Classifier: Operating System :: OS Independent
Classifier: License :: OSI Approved :: MIT License
Requires-Python: >=3.6
